wudz_pscan.py
wuddz_pscan-1.0.0.dist-info/METADATA
wuddz_pscan-1.0.0.dist-info/WHEEL
wuddz_pscan-1.0.0.dist-info/entry_points.txt
wuddz_pscan-1.0.0.dist-info/licenses/LICENSE
wuddz_pscan-1.0.0.dist-info/RECORD
