Metadata-Version: 2.1
Name: wuddz-pscan
Version: 1.0.0
Summary: Asynchronously Scan A Host(s)/Network(s)/IPRange(s) For Open TCP Ports.
Project-URL: Homepage, https://github.com/wuddz-devs/wuddz-port-scanner
Author-email: Wuddz-Devs <wuddz_devs@protonmail.com>
License: MIT License
License-File: LICENSE
Keywords: hosts,ip,ports,scan,scanner,tcp
Classifier: License :: OSI Approved :: MIT License
Classifier: Programming Language :: Python
Classifier: Programming Language :: Python :: 3.7
Classifier: Programming Language :: Python :: 3.8
Classifier: Programming Language :: Python :: 3.9
Classifier: Programming Language :: Python :: 3.10
Requires-Python: >=3.7
